marzneshein/__init__.py
marzneshein/api.py
marzneshein/models.py
marzneshein-0.1.2.dist-info/LICENSE
marzneshein-0.1.2.dist-info/METADATA
marzneshein-0.1.2.dist-info/WHEEL
marzneshein-0.1.2.dist-info/top_level.txt
marzneshein-0.1.2.dist-info/RECORD
