Metadata-Version: 2.1
Name: marzneshein
Version: 0.1.2
Summary: Marzneshein Control API Client
Home-page: https://github.com/sm1ky/marzneshein_api
Author: Artem
Author-email: contact@sm1ky.com
Classifier: Programming Language :: Python :: 3
Classifier: License :: OSI Approved :: MIT License
Classifier: Operating System :: OS Independent
Requires-Python: >=3.10
License-File: LICENSE
Requires-Dist: httpx
Requires-Dist: pydantic
